LICENSE.txt
MANIFEST.in
README.md
setup.py
completeit/__init__.py
completeit/forms.py
completeit/models.py
completeit/serializer.py
completeit/tests.py
completeit/urls.py
completeit/views.py
completeit.egg-info/PKG-INFO
completeit.egg-info/SOURCES.txt
completeit.egg-info/dependency_links.txt
completeit.egg-info/not-zip-safe
completeit.egg-info/top_level.txt
completeit/media/.DS_Store
completeit/media/completeit/.DS_Store
completeit/media/completeit/css/jquery-ui.css
completeit/media/completeit/js/completeit.js
completeit/media/completeit/js/jquery-ui.js
completeit/media/completeit/js/jquery.js