Metadata-Version: 1.0
Name: completeit
Version: 0.0.1
Summary: django_completeit
Home-page: http://github.com/comogo/django_completeit
Author: Mateus Lorandi dos Santos
Author-email: mcomogo@gmail.com
License: MIT
Keywords: ajax,django,autocomplete
Platform: UNKNOWN
Classifier: Programming Language :: Python
Classifier: Topic :: Software Development :: Libraries :: Python Modules
Classifier: Framework :: Django
Classifier: Environment :: Web Environment
